AUTHORS.rst
CONTRIBUTING.rst
HISTORY.rst
LICENSE
MANIFEST.in
README.rst
setup.cfg
setup.py
docs/Makefile
docs/authors.rst
docs/conf.py
docs/contributing.rst
docs/history.rst
docs/index.rst
docs/installation.rst
docs/make.bat
docs/readme.rst
docs/usage.rst
jsonforge/__init__.py
jsonforge/cmdline.py
jsonforge/helpers.py
jsonforge/jpfunctions.py
jsonforge.egg-info/PKG-INFO
jsonforge.egg-info/SOURCES.txt
jsonforge.egg-info/dependency_links.txt
jsonforge.egg-info/entry_points.txt
jsonforge.egg-info/not-zip-safe
jsonforge.egg-info/requires.txt
jsonforge.egg-info/top_level.txt
jsonforge/pipelines/__init__.py
jsonforge/pipelines/css.py
jsonforge/pipelines/debug.py
jsonforge/pipelines/jmespath.py
jsonforge/pipelines/join.py
jsonforge/pipelines/nop.py
jsonforge/pipelines/sqlite.py
jsonforge/pipelines/unique.py
jsonforge/pipelines/xpath.py
jsonforge/processor/__init__.py
jsonforge/processor/job.py
jsonforge/processor/output.py
jsonforge/processor/pipeline.py
jsonforge/processor/processor.py
jsonforge/processor/textdata.py
jsonforge/processor/storage/__init__.py
jsonforge/processor/storage/local.py
jsonforge/processor/storage/s3.py
tests/__init__.py
tests/test_helpers.py
tests/test_jpfunctions.py
tests/test_textpipeline.py
tests/processor/__init__.py
tests/processor/test_textdata.py
tests/processor/storage/__init__.py
tests/processor/storage/test_local.py